graphql_config/__init__.py
graphql_config-0.0.1.dist-info/LICENSE
graphql_config-0.0.1.dist-info/WHEEL
graphql_config-0.0.1.dist-info/METADATA
graphql_config-0.0.1.dist-info/RECORD
